LICENSE
MANIFEST.in
README.rst
setup.py
django_usuario.egg-info/PKG-INFO
django_usuario.egg-info/SOURCES.txt
django_usuario.egg-info/dependency_links.txt
django_usuario.egg-info/pbr.json
django_usuario.egg-info/top_level.txt
usuario/__init__.py
usuario/forms.py
usuario/models.py
usuario/tests.py