Metadata-Version: 1.1
Name: django-usuario
Version: 0.4
Summary: Extension to model User.
Home-page: https://github.com/dyachan/django-usuario
Author: Diego Yachan
Author-email: diego.yachan@gmail.com
License: MIT License
Keywords: django user
Platform: UNKNOWN
Classifier: Environment :: Web Environment
Classifier: Framework :: Django
Classifier: Intended Audience :: Developers
Classifier: License :: OSI Approved :: MIT License
Classifier: Operating System :: OS Independent
Classifier: Programming Language :: Python
Classifier: Programming Language :: Python :: 3
Classifier: Programming Language :: Python :: 3.2
Classifier: Programming Language :: Python :: 3.3
Classifier: Programming Language :: Python :: 3.4
Classifier: Topic :: Internet :: WWW/HTTP
Classifier: Topic :: Internet :: WWW/HTTP :: Dynamic Content
